fabricatio_core/__init__.py
fabricatio_core/capabilities/__init__.py
fabricatio_core/capabilities/propose.py
fabricatio_core/capabilities/usages.py
fabricatio_core/decorators.py
fabricatio_core/emitter.py
fabricatio_core/journal.py
fabricatio_core/models/__init__.py
fabricatio_core/models/action.py
fabricatio_core/models/containers.py
fabricatio_core/models/generic.py
fabricatio_core/models/kwargs_types.py
fabricatio_core/models/llm.py
fabricatio_core/models/role.py
fabricatio_core/models/task.py
fabricatio_core/parser.py
fabricatio_core/py.typed
fabricatio_core/rust.cpython-313-x86_64-linux-gnu.so
fabricatio_core/rust.pyi
fabricatio_core/utils.py
fabricatio_core-0.5.3.dist-info/METADATA
fabricatio_core-0.5.3.dist-info/WHEEL
fabricatio_core-0.5.3.dist-info/licenses/LICENSE
fabricatio_core-0.5.3.dist-info/RECORD
