Metadata-Version: 2.4
Name: fabricatio-core
Version: 0.5.3
Classifier: License :: OSI Approved :: MIT License
Classifier: Programming Language :: Python :: 3.12
Classifier: Programming Language :: Python :: 3.13
Classifier: Programming Language :: Python :: 3.14
Classifier: Programming Language :: Python :: Implementation :: CPython
Classifier: Framework :: AsyncIO
Classifier: Framework :: Pydantic :: 2
Classifier: Typing :: Typed
Requires-Dist: asyncio>=3.4.3
Requires-Dist: asyncstdlib>=3.13.0
Requires-Dist: json-repair>=0.39.1
Requires-Dist: litellm>=1.60.0
Requires-Dist: more-itertools>=10.6.0
Requires-Dist: pydantic>=2.10.6
Requires-Dist: rich>=13.9.4
Requires-Dist: orjson>=3.10.18
License-File: LICENSE
Summary: A foundational Python library providing core components for building LLM-driven applications using an event-based agent structure.
Author-email: Whth <zettainspector@foxmail.com>
Requires-Python: >=3.12, <3.15
Project-URL: Homepage, https://github.com/Whth/fabricatio
Project-URL: Issues, https://github.com/Whth/fabricatio/issues
Project-URL: Repository, https://github.com/Whth/fabricatio
